{
  "drivers": [
    {
      "driver_id": 809,
      "team": "Mercedes AMG Petronas F1 Team",
      "best_ms": 89493,
      "best_raw": "1:29.493",
      "source_session": "Q3"
    },
    {
      "driver_id": 805,
      "team": "Mercedes AMG Petronas F1 Team",
      "best_ms": 89570,
      "best_raw": "1:29.570",
      "source_session": "Q3"
    },
    {
      "driver_id": 813,
      "team": "Scuderia Ferrari",
      "best_ms": 90012,
      "best_raw": "1:30.012",
      "source_session": "Q3"
    },
    {
      "driver_id": 771,
      "team": "Scuderia Ferrari",
      "best_ms": 90244,
      "best_raw": "1:30.244",
      "source_session": "Q3"
    },
    {
      "driver_id": 833,
      "team": "Red Bull Racing/TAG",
      "best_ms": 90854,
      "best_raw": "1:30.854",
      "source_session": "Q3"
    },
    {
      "driver_id": 842,
      "team": "Williams Martini Racing/Mercedes",
      "best_ms": 90931,
      "best_raw": "1:30.931",
      "source_session": "Q2"
    },
    {
      "driver_id": 774,
      "team": "Williams Martini Racing/Mercedes",
      "best_ms": 91155,
      "best_raw": "1:31.155",
      "source_session": "Q3"
    },
    {
      "driver_id": 824,
      "team": "Sahara Force India F1 Team/Mercedes",
      "best_ms": 91604,
      "best_raw": "1:31.604",
      "source_session": "Q2"
    },
    {
      "driver_id": 863,
      "team": "Scuderia Toro Rosso/Ferrari",
      "best_ms": 91716,
      "best_raw": "1:31.716",
      "source_session": "Q1"
    },
    {
      "driver_id": 819,
      "team": "Haas F1 Team/Ferrari",
      "best_ms": 91756,
      "best_raw": "1:31.756",
      "source_session": "Q2"
    },
    {
      "driver_id": 864,
      "team": "Scuderia Toro Rosso/Ferrari",
      "best_ms": 91771,
      "best_raw": "1:31.772",
      "source_session": "Q2"
    },
    {
      "driver_id": 869,
      "team": "McLaren-Honda Formula 1 Team",
      "best_ms": 91934,
      "best_raw": "1:31.934",
      "source_session": "Q2"
    },
    {
      "driver_id": 845,
      "team": "Haas F1 Team/Ferrari",
      "best_ms": 91945,
      "best_raw": "1:31.945",
      "source_session": "Q2"
    },
    {
      "driver_id": 764,
      "team": "McLaren-Honda Formula 1 Team",
      "best_ms": 91976,
      "best_raw": "1:31.976",
      "source_session": "Q1"
    },
    {
      "driver_id": 852,
      "team": "Red Bull Racing/TAG",
      "best_ms": 92241,
      "best_raw": "1:32.241",
      "source_session": "Q2"
    },
    {
      "driver_id": 870,
      "team": "Manor Racing/Mercedes",
      "best_ms": 92806,
      "best_raw": "1:32.806",
      "source_session": "Q1"
    },
    {
      "driver_id": 848,
      "team": "Sauber F1 Team/Ferrari",
      "best_ms": 92840,
      "best_raw": "1:32.840",
      "source_session": "Q1"
    },
    {
      "driver_id": 831,
      "team": "Sahara Force India F1 Team/Mercedes",
      "best_ms": 92911,
      "best_raw": "1:32.911",
      "source_session": "Q1"
    },
    {
      "driver_id": 854,
      "team": "Renault Sport Formula One Team",
      "best_ms": 93181,
      "best_raw": "1:33.181",
      "source_session": "Q1"
    },
    {
      "driver_id": 846,
      "team": "Renault Sport Formula One Team",
      "best_ms": 93438,
      "best_raw": "1:33.438",
      "source_session": "Q1"
    },
    {
      "driver_id": 862,
      "team": "Sauber F1 Team/Ferrari",
      "best_ms": 94013,
      "best_raw": "1:34.013",
      "source_session": "EL3"
    },
    {
      "driver_id": 866,
      "team": "Manor Racing/Mercedes",
      "best_ms": 94190,
      "best_raw": "1:34.190",
      "source_session": "Q1"
    },
    {
      "driver_id": 865,
      "team": "",
      "best_ms": 97287,
      "best_raw": "1:37.287",
      "source_session": "EL1"
    }
  ],
  "race_id": 937,
  "updated_at": "2025-10-21T14:36:37.128237Z",
  "schema": "v3.4"
}