{
  "race_id": 900,
  "meta": {
    "year": 2014,
    "round": 3,
    "name": "GP3",
    "circuit": "Bahrain International Circuit",
    "country": "Bahrain",
    "date": null
  },
  "sessions": [
    {
      "code": "EL1",
      "name": "Essais Libres 1",
      "nb_rows": 22,
      "best_pos": 1,
      "best_ms": 97502,
      "rows": [
        {
          "race_id": 900,
          "driver_id": 756,
          "team": "mclaren mercedes",
          "best_lap_time_raw": "01:38.636",
          "best_lap_ms": 98636,
          "position": 5,
          "year": 2014,
          "source_name": "EL1_BRUT_ALL_WITH_ID"
        },
        {
          "race_id": 900,
          "driver_id": 759,
          "team": "ferrari",
          "best_lap_time_raw": "01:37.953",
          "best_lap_ms": 97953,
          "position": 3,
          "year": 2014,
          "source_name": "EL1_BRUT_ALL_WITH_ID"
        },
        {
          "race_id": 900,
          "driver_id": 763,
          "team": "ferrari",
          "best_lap_time_raw": "01:38.783",
          "best_lap_ms": 98783,
          "position": 6,
          "year": 2014,
          "source_name": "EL1_BRUT_ALL_WITH_ID"
        },
        {
          "race_id": 900,
          "driver_id": 766,
          "team": "williams mercedes",
          "best_lap_time_raw": "01:39.533",
          "best_lap_ms": 99533,
          "position": 11,
          "year": 2014,
          "source_name": "EL1_BRUT_ALL_WITH_ID"
        },
        {
          "race_id": 900,
          "driver_id": 797,
          "team": "mercedes",
          "best_lap_time_raw": "01:37.733",
          "best_lap_ms": 97733,
          "position": 2,
          "year": 2014,
          "source_name": "EL1_BRUT_ALL_WITH_ID"
        },
        {
          "race_id": 900,
          "driver_id": 801,
          "team": "mercedes",
          "best_lap_time_raw": "01:37.502",
          "best_lap_ms": 97502,
          "position": 1,
          "year": 2014,
          "source_name": "EL1_BRUT_ALL_WITH_ID"
        },
        {
          "race_id": 900,
          "driver_id": 804,
          "team": "sauber ferrari",
          "best_lap_time_raw": "01:40.652",
          "best_lap_ms": 100652,
          "position": 15,
          "year": 2014,
          "source_name": "EL1_BRUT_ALL_WITH_ID"
        },
        {
          "race_id": 900,
          "driver_id": 805,
          "team": "red bull racing renault",
          "best_lap_time_raw": "01:39.389",
          "best_lap_ms": 99389,
          "position": 10,
          "year": 2014,
          "source_name": "EL1_BRUT_ALL_WITH_ID"
        },
        {
          "race_id": 900,
          "driver_id": 811,
          "team": "lotus renault",
          "best_lap_time_raw": "01:41.036",
          "best_lap_ms": 101036,
          "position": 19,
          "year": 2014,
          "source_name": "EL1_BRUT_ALL_WITH_ID"
        },
        {
          "race_id": 900,
          "driver_id": 816,
          "team": "force india mercedes",
          "best_lap_time_raw": "01:38.122",
          "best_lap_ms": 98122,
          "position": 4,
          "year": 2014,
          "source_name": "EL1_BRUT_ALL_WITH_ID"
        },
        {
          "race_id": 900,
          "driver_id": 822,
          "team": "lotus renault",
          "best_lap_time_raw": "01:40.793",
          "best_lap_ms": 100793,
          "position": 16,
          "year": 2014,
          "source_name": "EL1_BRUT_ALL_WITH_ID"
        },
        {
          "race_id": 900,
          "driver_id": 823,
          "team": "force india mercedes",
          "best_lap_time_raw": "01:39.102",
          "best_lap_ms": 99102,
          "position": 9,
          "year": 2014,
          "source_name": "EL1_BRUT_ALL_WITH_ID"
        },
        {
          "race_id": 900,
          "driver_id": 825,
          "team": "red bull racing renault",
          "best_lap_time_raw": "01:40.406",
          "best_lap_ms": 100406,
          "position": 14,
          "year": 2014,
          "source_name": "EL1_BRUT_ALL_WITH_ID"
        },
        {
          "race_id": 900,
          "driver_id": 832,
          "team": "str renault",
          "best_lap_time_raw": "01:39.862",
          "best_lap_ms": 99862,
          "position": 12,
          "year": 2014,
          "source_name": "EL1_BRUT_ALL_WITH_ID"
        },
        {
          "race_id": 900,
          "driver_id": 833,
          "team": "marussia ferrari",
          "best_lap_time_raw": "01:40.889",
          "best_lap_ms": 100889,
          "position": 17,
          "year": 2014,
          "source_name": "EL1_BRUT_ALL_WITH_ID"
        },
        {
          "race_id": 900,
          "driver_id": 836,
          "team": "marussia ferrari",
          "best_lap_time_raw": "01:41.794",
          "best_lap_ms": 101794,
          "position": 20,
          "year": 2014,
          "source_name": "EL1_BRUT_ALL_WITH_ID"
        },
        {
          "race_id": 900,
          "driver_id": 839,
          "team": "sauber ferrari",
          "best_lap_time_raw": "01:40.913",
          "best_lap_ms": 100913,
          "position": 18,
          "year": 2014,
          "source_name": "EL1_BRUT_ALL_WITH_ID"
        },
        {
          "race_id": 900,
          "driver_id": 840,
          "team": "caterham renault",
          "best_lap_time_raw": "01:42.711",
          "best_lap_ms": 102711,
          "position": 22,
          "year": 2014,
          "source_name": "EL1_BRUT_ALL_WITH_ID"
        },
        {
          "race_id": 900,
          "driver_id": 842,
          "team": "caterham renault",
          "best_lap_time_raw": "01:42.417",
          "best_lap_ms": 102417,
          "position": 21,
          "year": 2014,
          "source_name": "EL1_BRUT_ALL_WITH_ID"
        },
        {
          "race_id": 900,
          "driver_id": 844,
          "team": "str renault",
          "best_lap_time_raw": "01:39.056",
          "best_lap_ms": 99056,
          "position": 8,
          "year": 2014,
          "source_name": "EL1_BRUT_ALL_WITH_ID"
        },
        {
          "race_id": 900,
          "driver_id": 846,
          "team": "mclaren mercedes",
          "best_lap_time_raw": "01:38.949",
          "best_lap_ms": 98949,
          "position": 7,
          "year": 2014,
          "source_name": "EL1_BRUT_ALL_WITH_ID"
        },
        {
          "race_id": 900,
          "driver_id": 854,
          "team": "williams mercedes",
          "best_lap_time_raw": "01:40.078",
          "best_lap_ms": 100078,
          "position": 13,
          "year": 2014,
          "source_name": "EL1_BRUT_ALL_WITH_ID"
        }
      ]
    },
    {
      "code": "EL2",
      "name": "Essais Libres 2",
      "nb_rows": 22,
      "best_pos": 1,
      "best_ms": 94325,
      "rows": [
        {
          "race_id": 900,
          "driver_id": 756,
          "team": "mclaren mercedes",
          "best_lap_time_raw": "01:35.528",
          "best_lap_ms": 95528,
          "position": 6,
          "year": 2014,
          "source_name": "EL2_BRUT_ALL_WITH_ID"
        },
        {
          "race_id": 900,
          "driver_id": 759,
          "team": "ferrari",
          "best_lap_time_raw": "01:35.360",
          "best_lap_ms": 95360,
          "position": 3,
          "year": 2014,
          "source_name": "EL2_BRUT_ALL_WITH_ID"
        },
        {
          "race_id": 900,
          "driver_id": 763,
          "team": "ferrari",
          "best_lap_time_raw": "01:36.366",
          "best_lap_ms": 96366,
          "position": 14,
          "year": 2014,
          "source_name": "EL2_BRUT_ALL_WITH_ID"
        },
        {
          "race_id": 900,
          "driver_id": 766,
          "team": "williams mercedes",
          "best_lap_time_raw": "01:35.442",
          "best_lap_ms": 95442,
          "position": 5,
          "year": 2014,
          "source_name": "EL2_BRUT_ALL_WITH_ID"
        },
        {
          "race_id": 900,
          "driver_id": 797,
          "team": "mercedes",
          "best_lap_time_raw": "01:34.690",
          "best_lap_ms": 94690,
          "position": 2,
          "year": 2014,
          "source_name": "EL2_BRUT_ALL_WITH_ID"
        },
        {
          "race_id": 900,
          "driver_id": 801,
          "team": "mercedes",
          "best_lap_time_raw": "01:34.325",
          "best_lap_ms": 94325,
          "position": 1,
          "year": 2014,
          "source_name": "EL2_BRUT_ALL_WITH_ID"
        },
        {
          "race_id": 900,
          "driver_id": 804,
          "team": "sauber ferrari",
          "best_lap_time_raw": "01:36.962",
          "best_lap_ms": 96962,
          "position": 15,
          "year": 2014,
          "source_name": "EL2_BRUT_ALL_WITH_ID"
        },
        {
          "race_id": 900,
          "driver_id": 805,
          "team": "red bull racing renault",
          "best_lap_time_raw": "01:35.606",
          "best_lap_ms": 95606,
          "position": 7,
          "year": 2014,
          "source_name": "EL2_BRUT_ALL_WITH_ID"
        },
        {
          "race_id": 900,
          "driver_id": 811,
          "team": "lotus renault",
          "best_lap_time_raw": "01:37.599",
          "best_lap_ms": 97599,
          "position": 18,
          "year": 2014,
          "source_name": "EL2_BRUT_ALL_WITH_ID"
        },
        {
          "race_id": 900,
          "driver_id": 812,
          "team": "caterham renault",
          "best_lap_time_raw": "01:38.257",
          "best_lap_ms": 98257,
          "position": 21,
          "year": 2014,
          "source_name": "EL2_BRUT_ALL_WITH_ID"
        },
        {
          "race_id": 900,
          "driver_id": 816,
          "team": "force india mercedes",
          "best_lap_time_raw": "01:35.998",
          "best_lap_ms": 95998,
          "position": 13,
          "year": 2014,
          "source_name": "EL2_BRUT_ALL_WITH_ID"
        },
        {
          "race_id": 900,
          "driver_id": 822,
          "team": "lotus renault",
          "best_lap_time_raw": "01:37.259",
          "best_lap_ms": 97259,
          "position": 17,
          "year": 2014,
          "source_name": "EL2_BRUT_ALL_WITH_ID"
        },
        {
          "race_id": 900,
          "driver_id": 823,
          "team": "force india mercedes",
          "best_lap_time_raw": "01:35.802",
          "best_lap_ms": 95802,
          "position": 10,
          "year": 2014,
          "source_name": "EL2_BRUT_ALL_WITH_ID"
        },
        {
          "race_id": 900,
          "driver_id": 825,
          "team": "red bull racing renault",
          "best_lap_time_raw": "01:35.433",
          "best_lap_ms": 95433,
          "position": 4,
          "year": 2014,
          "source_name": "EL2_BRUT_ALL_WITH_ID"
        },
        {
          "race_id": 900,
          "driver_id": 832,
          "team": "str renault",
          "best_lap_time_raw": "01:35.972",
          "best_lap_ms": 95972,
          "position": 12,
          "year": 2014,
          "source_name": "EL2_BRUT_ALL_WITH_ID"
        },
        {
          "race_id": 900,
          "driver_id": 833,
          "team": "marussia ferrari",
          "best_lap_time_raw": "01:37.800",
          "best_lap_ms": 97800,
          "position": 19,
          "year": 2014,
          "source_name": "EL2_BRUT_ALL_WITH_ID"
        },
        {
          "race_id": 900,
          "driver_id": 834,
          "team": "williams mercedes",
          "best_lap_time_raw": "01:35.920",
          "best_lap_ms": 95920,
          "position": 11,
          "year": 2014,
          "source_name": "EL2_BRUT_ALL_WITH_ID"
        },
        {
          "race_id": 900,
          "driver_id": 836,
          "team": "marussia ferrari",
          "best_lap_time_raw": "01:38.247",
          "best_lap_ms": 98247,
          "position": 20,
          "year": 2014,
          "source_name": "EL2_BRUT_ALL_WITH_ID"
        },
        {
          "race_id": 900,
          "driver_id": 837,
          "team": "sauber ferrari",
          "best_lap_time_raw": "01:36.975",
          "best_lap_ms": 96975,
          "position": 16,
          "year": 2014,
          "source_name": "EL2_BRUT_ALL_WITH_ID"
        },
        {
          "race_id": 900,
          "driver_id": 840,
          "team": "caterham renault",
          "best_lap_time_raw": "01:39.136",
          "best_lap_ms": 99136,
          "position": 22,
          "year": 2014,
          "source_name": "EL2_BRUT_ALL_WITH_ID"
        },
        {
          "race_id": 900,
          "driver_id": 844,
          "team": "str renault",
          "best_lap_time_raw": "01:35.640",
          "best_lap_ms": 95640,
          "position": 8,
          "year": 2014,
          "source_name": "EL2_BRUT_ALL_WITH_ID"
        },
        {
          "race_id": 900,
          "driver_id": 846,
          "team": "mclaren mercedes",
          "best_lap_time_raw": "01:35.662",
          "best_lap_ms": 95662,
          "position": 9,
          "year": 2014,
          "source_name": "EL2_BRUT_ALL_WITH_ID"
        }
      ]
    },
    {
      "code": "EL3",
      "name": "Essais Libres 3",
      "nb_rows": 22,
      "best_pos": 1,
      "best_ms": 95324,
      "rows": [
        {
          "race_id": 900,
          "driver_id": 764,
          "team": "mclaren mercedes",
          "best_lap_time_raw": "01:36.394",
          "best_lap_ms": 96394,
          "position": 6,
          "year": 2014,
          "source_name": "EL3_BRUT_ALL_WITH_ID"
        },
        {
          "race_id": 900,
          "driver_id": 767,
          "team": "ferrari",
          "best_lap_time_raw": "01:36.454",
          "best_lap_ms": 96454,
          "position": 7,
          "year": 2014,
          "source_name": "EL3_BRUT_ALL_WITH_ID"
        },
        {
          "race_id": 900,
          "driver_id": 771,
          "team": "ferrari",
          "best_lap_time_raw": "01:36.772",
          "best_lap_ms": 96772,
          "position": 10,
          "year": 2014,
          "source_name": "EL3_BRUT_ALL_WITH_ID"
        },
        {
          "race_id": 900,
          "driver_id": 774,
          "team": "williams mercedes",
          "best_lap_time_raw": "01:36.364",
          "best_lap_ms": 96364,
          "position": 5,
          "year": 2014,
          "source_name": "EL3_BRUT_ALL_WITH_ID"
        },
        {
          "race_id": 900,
          "driver_id": 805,
          "team": "mercedes",
          "best_lap_time_raw": "01:35.439",
          "best_lap_ms": 95439,
          "position": 2,
          "year": 2014,
          "source_name": "EL3_BRUT_ALL_WITH_ID"
        },
        {
          "race_id": 900,
          "driver_id": 809,
          "team": "mercedes",
          "best_lap_time_raw": "01:35.324",
          "best_lap_ms": 95324,
          "position": 1,
          "year": 2014,
          "source_name": "EL3_BRUT_ALL_WITH_ID"
        },
        {
          "race_id": 900,
          "driver_id": 812,
          "team": "sauber ferrari",
          "best_lap_time_raw": "01:38.089",
          "best_lap_ms": 98089,
          "position": 15,
          "year": 2014,
          "source_name": "EL3_BRUT_ALL_WITH_ID"
        },
        {
          "race_id": 900,
          "driver_id": 813,
          "team": "red bull racing renault",
          "best_lap_time_raw": "01:39.225",
          "best_lap_ms": 99225,
          "position": 21,
          "year": 2014,
          "source_name": "EL3_BRUT_ALL_WITH_ID"
        },
        {
          "race_id": 900,
          "driver_id": 819,
          "team": "lotus renault",
          "best_lap_time_raw": "01:39.208",
          "best_lap_ms": 99208,
          "position": 20,
          "year": 2014,
          "source_name": "EL3_BRUT_ALL_WITH_ID"
        },
        {
          "race_id": 900,
          "driver_id": 820,
          "team": "caterham renault",
          "best_lap_time_raw": "01:38.400",
          "best_lap_ms": 98400,
          "position": 16,
          "year": 2014,
          "source_name": "EL3_BRUT_ALL_WITH_ID"
        },
        {
          "race_id": 900,
          "driver_id": 824,
          "team": "force india mercedes",
          "best_lap_time_raw": "01:36.455",
          "best_lap_ms": 96455,
          "position": 8,
          "year": 2014,
          "source_name": "EL3_BRUT_ALL_WITH_ID"
        },
        {
          "race_id": 900,
          "driver_id": 830,
          "team": "lotus renault",
          "best_lap_time_raw": "01:38.880",
          "best_lap_ms": 98880,
          "position": 18,
          "year": 2014,
          "source_name": "EL3_BRUT_ALL_WITH_ID"
        },
        {
          "race_id": 900,
          "driver_id": 831,
          "team": "force india mercedes",
          "best_lap_time_raw": "01:35.868",
          "best_lap_ms": 95868,
          "position": 3,
          "year": 2014,
          "source_name": "EL3_BRUT_ALL_WITH_ID"
        },
        {
          "race_id": 900,
          "driver_id": 833,
          "team": "red bull racing renault",
          "best_lap_time_raw": "01:37.119",
          "best_lap_ms": 97119,
          "position": 13,
          "year": 2014,
          "source_name": "EL3_BRUT_ALL_WITH_ID"
        },
        {
          "race_id": 900,
          "driver_id": 840,
          "team": "str renault",
          "best_lap_time_raw": "01:37.030",
          "best_lap_ms": 97030,
          "position": 12,
          "year": 2014,
          "source_name": "EL3_BRUT_ALL_WITH_ID"
        },
        {
          "race_id": 900,
          "driver_id": 841,
          "team": "marussia ferrari",
          "best_lap_time_raw": "01:38.736",
          "best_lap_ms": 98736,
          "position": 17,
          "year": 2014,
          "source_name": "EL3_BRUT_ALL_WITH_ID"
        },
        {
          "race_id": 900,
          "driver_id": 842,
          "team": "williams mercedes",
          "best_lap_time_raw": "01:36.116",
          "best_lap_ms": 96116,
          "position": 4,
          "year": 2014,
          "source_name": "EL3_BRUT_ALL_WITH_ID"
        },
        {
          "race_id": 900,
          "driver_id": 844,
          "team": "marussia ferrari",
          "best_lap_time_raw": "01:39.597",
          "best_lap_ms": 99597,
          "position": 22,
          "year": 2014,
          "source_name": "EL3_BRUT_ALL_WITH_ID"
        },
        {
          "race_id": 900,
          "driver_id": 845,
          "team": "sauber ferrari",
          "best_lap_time_raw": "01:37.325",
          "best_lap_ms": 97325,
          "position": 14,
          "year": 2014,
          "source_name": "EL3_BRUT_ALL_WITH_ID"
        },
        {
          "race_id": 900,
          "driver_id": 848,
          "team": "caterham renault",
          "best_lap_time_raw": "01:38.971",
          "best_lap_ms": 98971,
          "position": 19,
          "year": 2014,
          "source_name": "EL3_BRUT_ALL_WITH_ID"
        },
        {
          "race_id": 900,
          "driver_id": 852,
          "team": "str renault",
          "best_lap_time_raw": "01:36.680",
          "best_lap_ms": 96680,
          "position": 9,
          "year": 2014,
          "source_name": "EL3_BRUT_ALL_WITH_ID"
        },
        {
          "race_id": 900,
          "driver_id": 854,
          "team": "mclaren mercedes",
          "best_lap_time_raw": "01:36.822",
          "best_lap_ms": 96822,
          "position": 11,
          "year": 2014,
          "source_name": "EL3_BRUT_ALL_WITH_ID"
        }
      ]
    },
    {
      "code": "Q1",
      "name": "Q1",
      "nb_rows": 22,
      "best_pos": 1,
      "best_ms": 94874,
      "rows": [
        {
          "race_id": 900,
          "driver_id": 764,
          "team": "mclaren mercedes",
          "best_lap_time_raw": "01:35.699",
          "best_lap_ms": 95699,
          "position": 7,
          "year": 2014,
          "source_name": "Q1_BRUT_ALL_WITH_ID"
        },
        {
          "race_id": 900,
          "driver_id": 767,
          "team": "ferrari",
          "best_lap_time_raw": "01:35.251",
          "best_lap_ms": 95251,
          "position": 10,
          "year": 2014,
          "source_name": "Q1_BRUT_ALL_WITH_ID"
        },
        {
          "race_id": 900,
          "driver_id": 771,
          "team": "ferrari",
          "best_lap_time_raw": "01:35.234",
          "best_lap_ms": 95234,
          "position": 6,
          "year": 2014,
          "source_name": "Q1_BRUT_ALL_WITH_ID"
        },
        {
          "race_id": 900,
          "driver_id": 774,
          "team": "williams mercedes",
          "best_lap_time_raw": "01:35.085",
          "best_lap_ms": 95085,
          "position": 8,
          "year": 2014,
          "source_name": "Q1_BRUT_ALL_WITH_ID"
        },
        {
          "race_id": 900,
          "driver_id": 805,
          "team": "mercedes",
          "best_lap_time_raw": "01:35.439",
          "best_lap_ms": 95439,
          "position": 1,
          "year": 2014,
          "source_name": "Q1_BRUT_ALL_WITH_ID"
        },
        {
          "race_id": 900,
          "driver_id": 809,
          "team": "mercedes",
          "best_lap_time_raw": "01:35.323",
          "best_lap_ms": 95323,
          "position": 2,
          "year": 2014,
          "source_name": "Q1_BRUT_ALL_WITH_ID"
        },
        {
          "race_id": 900,
          "driver_id": 812,
          "team": "sauber ferrari",
          "best_lap_time_raw": "01:36.840",
          "best_lap_ms": 96840,
          "position": 18,
          "year": 2014,
          "source_name": "Q1_BRUT_ALL_WITH_ID"
        },
        {
          "race_id": 900,
          "driver_id": 813,
          "team": "red bull racing renault",
          "best_lap_time_raw": "01:35.549",
          "best_lap_ms": 95549,
          "position": 11,
          "year": 2014,
          "source_name": "Q1_BRUT_ALL_WITH_ID"
        },
        {
          "race_id": 900,
          "driver_id": 819,
          "team": "lotus renault",
          "best_lap_time_raw": "01:36.654",
          "best_lap_ms": 96654,
          "position": 16,
          "year": 2014,
          "source_name": "Q1_BRUT_ALL_WITH_ID"
        },
        {
          "race_id": 900,
          "driver_id": 820,
          "team": "caterham renault",
          "best_lap_time_raw": "01:37.085",
          "best_lap_ms": 97085,
          "position": 19,
          "year": 2014,
          "source_name": "Q1_BRUT_ALL_WITH_ID"
        },
        {
          "race_id": 900,
          "driver_id": 824,
          "team": "force india mercedes",
          "best_lap_time_raw": "01:34.874",
          "best_lap_ms": 94874,
          "position": 12,
          "year": 2014,
          "source_name": "Q1_BRUT_ALL_WITH_ID"
        },
        {
          "race_id": 900,
          "driver_id": 830,
          "team": "lotus renault",
          "best_lap_time_raw": "01:36.663",
          "best_lap_ms": 96663,
          "position": 17,
          "year": 2014,
          "source_name": "Q1_BRUT_ALL_WITH_ID"
        },
        {
          "race_id": 900,
          "driver_id": 831,
          "team": "force india mercedes",
          "best_lap_time_raw": "01:34.998",
          "best_lap_ms": 94998,
          "position": 5,
          "year": 2014,
          "source_name": "Q1_BRUT_ALL_WITH_ID"
        },
        {
          "race_id": 900,
          "driver_id": 833,
          "team": "red bull racing renault",
          "best_lap_time_raw": "01:36.220",
          "best_lap_ms": 96220,
          "position": 3,
          "year": 2014,
          "source_name": "Q1_BRUT_ALL_WITH_ID"
        },
        {
          "race_id": 900,
          "driver_id": 840,
          "team": "str renault",
          "best_lap_time_raw": "01:35.815",
          "best_lap_ms": 95815,
          "position": 14,
          "year": 2014,
          "source_name": "Q1_BRUT_ALL_WITH_ID"
        },
        {
          "race_id": 900,
          "driver_id": 841,
          "team": "marussia ferrari",
          "best_lap_time_raw": "01:37.310",
          "best_lap_ms": 97310,
          "position": 20,
          "year": 2014,
          "source_name": "Q1_BRUT_ALL_WITH_ID"
        },
        {
          "race_id": 900,
          "driver_id": 842,
          "team": "williams mercedes",
          "best_lap_time_raw": "01:34.934",
          "best_lap_ms": 94934,
          "position": 4,
          "year": 2014,
          "source_name": "Q1_BRUT_ALL_WITH_ID"
        },
        {
          "race_id": 900,
          "driver_id": 844,
          "team": "marussia ferrari",
          "best_lap_time_raw": "01:37.913",
          "best_lap_ms": 97913,
          "position": 22,
          "year": 2014,
          "source_name": "Q1_BRUT_ALL_WITH_ID"
        },
        {
          "race_id": 900,
          "driver_id": 845,
          "team": "sauber ferrari",
          "best_lap_time_raw": "01:36.567",
          "best_lap_ms": 96567,
          "position": 15,
          "year": 2014,
          "source_name": "Q1_BRUT_ALL_WITH_ID"
        },
        {
          "race_id": 900,
          "driver_id": 848,
          "team": "caterham renault",
          "best_lap_time_raw": "01:37.875",
          "best_lap_ms": 97875,
          "position": 21,
          "year": 2014,
          "source_name": "Q1_BRUT_ALL_WITH_ID"
        },
        {
          "race_id": 900,
          "driver_id": 852,
          "team": "str renault",
          "best_lap_time_raw": "01:35.395",
          "best_lap_ms": 95395,
          "position": 13,
          "year": 2014,
          "source_name": "Q1_BRUT_ALL_WITH_ID"
        },
        {
          "race_id": 900,
          "driver_id": 854,
          "team": "mclaren mercedes",
          "best_lap_time_raw": "01:35.288",
          "best_lap_ms": 95288,
          "position": 9,
          "year": 2014,
          "source_name": "Q1_BRUT_ALL_WITH_ID"
        }
      ]
    },
    {
      "code": "Q2",
      "name": "Q2",
      "nb_rows": 22,
      "best_pos": 1,
      "best_ms": 93708,
      "rows": [
        {
          "race_id": 900,
          "driver_id": 764,
          "team": "mclaren mercedes",
          "best_lap_time_raw": "01:34.714",
          "best_lap_ms": 94714,
          "position": 7,
          "year": 2014,
          "source_name": "Q2_BRUT_ALL_WITH_ID"
        },
        {
          "race_id": 900,
          "driver_id": 767,
          "team": "ferrari",
          "best_lap_time_raw": "01:34.723",
          "best_lap_ms": 94723,
          "position": 10,
          "year": 2014,
          "source_name": "Q2_BRUT_ALL_WITH_ID"
        },
        {
          "race_id": 900,
          "driver_id": 771,
          "team": "ferrari",
          "best_lap_time_raw": "01:34.925",
          "best_lap_ms": 94925,
          "position": 6,
          "year": 2014,
          "source_name": "Q2_BRUT_ALL_WITH_ID"
        },
        {
          "race_id": 900,
          "driver_id": 774,
          "team": "williams mercedes",
          "best_lap_time_raw": "01:34.842",
          "best_lap_ms": 94842,
          "position": 8,
          "year": 2014,
          "source_name": "Q2_BRUT_ALL_WITH_ID"
        },
        {
          "race_id": 900,
          "driver_id": 803,
          "team": "sauber ferrari",
          "best_lap_time_raw": "",
          "best_lap_ms": null,
          "position": 18,
          "year": 2014,
          "source_name": "Q2_BRUT_ALL_WITH_ID"
        },
        {
          "race_id": 900,
          "driver_id": 805,
          "team": "mercedes",
          "best_lap_time_raw": "01:33.708",
          "best_lap_ms": 93708,
          "position": 1,
          "year": 2014,
          "source_name": "Q2_BRUT_ALL_WITH_ID"
        },
        {
          "race_id": 900,
          "driver_id": 809,
          "team": "mercedes",
          "best_lap_time_raw": "01:33.872",
          "best_lap_ms": 93872,
          "position": 2,
          "year": 2014,
          "source_name": "Q2_BRUT_ALL_WITH_ID"
        },
        {
          "race_id": 900,
          "driver_id": 811,
          "team": "caterham renault",
          "best_lap_time_raw": "",
          "best_lap_ms": null,
          "position": 19,
          "year": 2014,
          "source_name": "Q2_BRUT_ALL_WITH_ID"
        },
        {
          "race_id": 900,
          "driver_id": 813,
          "team": "red bull racing renault",
          "best_lap_time_raw": "01:34.985",
          "best_lap_ms": 94985,
          "position": 11,
          "year": 2014,
          "source_name": "Q2_BRUT_ALL_WITH_ID"
        },
        {
          "race_id": 900,
          "driver_id": 819,
          "team": "lotus renault",
          "best_lap_time_raw": "01:35.908",
          "best_lap_ms": 95908,
          "position": 16,
          "year": 2014,
          "source_name": "Q2_BRUT_ALL_WITH_ID"
        },
        {
          "race_id": 900,
          "driver_id": 821,
          "team": "lotus renault",
          "best_lap_time_raw": "",
          "best_lap_ms": null,
          "position": 17,
          "year": 2014,
          "source_name": "Q2_BRUT_ALL_WITH_ID"
        },
        {
          "race_id": 900,
          "driver_id": 824,
          "team": "force india mercedes",
          "best_lap_time_raw": "01:35.116",
          "best_lap_ms": 95116,
          "position": 12,
          "year": 2014,
          "source_name": "Q2_BRUT_ALL_WITH_ID"
        },
        {
          "race_id": 900,
          "driver_id": 831,
          "team": "force india mercedes",
          "best_lap_time_raw": "01:34.747",
          "best_lap_ms": 94747,
          "position": 5,
          "year": 2014,
          "source_name": "Q2_BRUT_ALL_WITH_ID"
        },
        {
          "race_id": 900,
          "driver_id": 832,
          "team": "marussia ferrari",
          "best_lap_time_raw": "",
          "best_lap_ms": null,
          "position": 20,
          "year": 2014,
          "source_name": "Q2_BRUT_ALL_WITH_ID"
        },
        {
          "race_id": 900,
          "driver_id": 833,
          "team": "red bull racing renault",
          "best_lap_time_raw": "01:34.592",
          "best_lap_ms": 94592,
          "position": 3,
          "year": 2014,
          "source_name": "Q2_BRUT_ALL_WITH_ID"
        },
        {
          "race_id": 900,
          "driver_id": 835,
          "team": "marussia ferrari",
          "best_lap_time_raw": "",
          "best_lap_ms": null,
          "position": 22,
          "year": 2014,
          "source_name": "Q2_BRUT_ALL_WITH_ID"
        },
        {
          "race_id": 900,
          "driver_id": 839,
          "team": "caterham renault",
          "best_lap_time_raw": "",
          "best_lap_ms": null,
          "position": 21,
          "year": 2014,
          "source_name": "Q2_BRUT_ALL_WITH_ID"
        },
        {
          "race_id": 900,
          "driver_id": 840,
          "team": "str renault",
          "best_lap_time_raw": "01:35.286",
          "best_lap_ms": 95286,
          "position": 14,
          "year": 2014,
          "source_name": "Q2_BRUT_ALL_WITH_ID"
        },
        {
          "race_id": 900,
          "driver_id": 842,
          "team": "williams mercedes",
          "best_lap_time_raw": "01:34.842",
          "best_lap_ms": 94842,
          "position": 4,
          "year": 2014,
          "source_name": "Q2_BRUT_ALL_WITH_ID"
        },
        {
          "race_id": 900,
          "driver_id": 845,
          "team": "sauber ferrari",
          "best_lap_time_raw": "01:35.891",
          "best_lap_ms": 95891,
          "position": 15,
          "year": 2014,
          "source_name": "Q2_BRUT_ALL_WITH_ID"
        },
        {
          "race_id": 900,
          "driver_id": 852,
          "team": "str renault",
          "best_lap_time_raw": "01:35.145",
          "best_lap_ms": 95145,
          "position": 13,
          "year": 2014,
          "source_name": "Q2_BRUT_ALL_WITH_ID"
        },
        {
          "race_id": 900,
          "driver_id": 854,
          "team": "mclaren mercedes",
          "best_lap_time_raw": "01:34.904",
          "best_lap_ms": 94904,
          "position": 9,
          "year": 2014,
          "source_name": "Q2_BRUT_ALL_WITH_ID"
        }
      ]
    },
    {
      "code": "Q3",
      "name": "Q3",
      "nb_rows": 22,
      "best_pos": 1,
      "best_ms": null,
      "rows": [
        {
          "race_id": 900,
          "driver_id": 764,
          "team": "mclaren mercedes",
          "best_lap_time_raw": null,
          "best_lap_ms": null,
          "position": 7,
          "year": 2014,
          "source_name": "Q3_BRUT_ALL_WITH_ID"
        },
        {
          "race_id": 900,
          "driver_id": 767,
          "team": "ferrari",
          "best_lap_time_raw": null,
          "best_lap_ms": null,
          "position": 10,
          "year": 2014,
          "source_name": "Q3_BRUT_ALL_WITH_ID"
        },
        {
          "race_id": 900,
          "driver_id": 771,
          "team": "ferrari",
          "best_lap_time_raw": null,
          "best_lap_ms": null,
          "position": 6,
          "year": 2014,
          "source_name": "Q3_BRUT_ALL_WITH_ID"
        },
        {
          "race_id": 900,
          "driver_id": 774,
          "team": "williams mercedes",
          "best_lap_time_raw": null,
          "best_lap_ms": null,
          "position": 8,
          "year": 2014,
          "source_name": "Q3_BRUT_ALL_WITH_ID"
        },
        {
          "race_id": 900,
          "driver_id": 805,
          "team": "mercedes",
          "best_lap_time_raw": null,
          "best_lap_ms": null,
          "position": 1,
          "year": 2014,
          "source_name": "Q3_BRUT_ALL_WITH_ID"
        },
        {
          "race_id": 900,
          "driver_id": 809,
          "team": "mercedes",
          "best_lap_time_raw": null,
          "best_lap_ms": null,
          "position": 2,
          "year": 2014,
          "source_name": "Q3_BRUT_ALL_WITH_ID"
        },
        {
          "race_id": 900,
          "driver_id": 812,
          "team": "sauber ferrari",
          "best_lap_time_raw": null,
          "best_lap_ms": null,
          "position": 18,
          "year": 2014,
          "source_name": "Q3_BRUT_ALL_WITH_ID"
        },
        {
          "race_id": 900,
          "driver_id": 813,
          "team": "red bull racing renault",
          "best_lap_time_raw": null,
          "best_lap_ms": null,
          "position": 11,
          "year": 2014,
          "source_name": "Q3_BRUT_ALL_WITH_ID"
        },
        {
          "race_id": 900,
          "driver_id": 819,
          "team": "lotus renault",
          "best_lap_time_raw": null,
          "best_lap_ms": null,
          "position": 16,
          "year": 2014,
          "source_name": "Q3_BRUT_ALL_WITH_ID"
        },
        {
          "race_id": 900,
          "driver_id": 820,
          "team": "caterham renault",
          "best_lap_time_raw": null,
          "best_lap_ms": null,
          "position": 19,
          "year": 2014,
          "source_name": "Q3_BRUT_ALL_WITH_ID"
        },
        {
          "race_id": 900,
          "driver_id": 824,
          "team": "force india mercedes",
          "best_lap_time_raw": null,
          "best_lap_ms": null,
          "position": 12,
          "year": 2014,
          "source_name": "Q3_BRUT_ALL_WITH_ID"
        },
        {
          "race_id": 900,
          "driver_id": 830,
          "team": "lotus renault",
          "best_lap_time_raw": null,
          "best_lap_ms": null,
          "position": 17,
          "year": 2014,
          "source_name": "Q3_BRUT_ALL_WITH_ID"
        },
        {
          "race_id": 900,
          "driver_id": 831,
          "team": "force india mercedes",
          "best_lap_time_raw": null,
          "best_lap_ms": null,
          "position": 5,
          "year": 2014,
          "source_name": "Q3_BRUT_ALL_WITH_ID"
        },
        {
          "race_id": 900,
          "driver_id": 833,
          "team": "red bull racing renault",
          "best_lap_time_raw": null,
          "best_lap_ms": null,
          "position": 3,
          "year": 2014,
          "source_name": "Q3_BRUT_ALL_WITH_ID"
        },
        {
          "race_id": 900,
          "driver_id": 840,
          "team": "str renault",
          "best_lap_time_raw": null,
          "best_lap_ms": null,
          "position": 14,
          "year": 2014,
          "source_name": "Q3_BRUT_ALL_WITH_ID"
        },
        {
          "race_id": 900,
          "driver_id": 841,
          "team": "marussia ferrari",
          "best_lap_time_raw": null,
          "best_lap_ms": null,
          "position": 20,
          "year": 2014,
          "source_name": "Q3_BRUT_ALL_WITH_ID"
        },
        {
          "race_id": 900,
          "driver_id": 842,
          "team": "williams mercedes",
          "best_lap_time_raw": null,
          "best_lap_ms": null,
          "position": 4,
          "year": 2014,
          "source_name": "Q3_BRUT_ALL_WITH_ID"
        },
        {
          "race_id": 900,
          "driver_id": 844,
          "team": "marussia ferrari",
          "best_lap_time_raw": null,
          "best_lap_ms": null,
          "position": 22,
          "year": 2014,
          "source_name": "Q3_BRUT_ALL_WITH_ID"
        },
        {
          "race_id": 900,
          "driver_id": 845,
          "team": "sauber ferrari",
          "best_lap_time_raw": null,
          "best_lap_ms": null,
          "position": 15,
          "year": 2014,
          "source_name": "Q3_BRUT_ALL_WITH_ID"
        },
        {
          "race_id": 900,
          "driver_id": 848,
          "team": "caterham renault",
          "best_lap_time_raw": null,
          "best_lap_ms": null,
          "position": 21,
          "year": 2014,
          "source_name": "Q3_BRUT_ALL_WITH_ID"
        },
        {
          "race_id": 900,
          "driver_id": 852,
          "team": "str renault",
          "best_lap_time_raw": null,
          "best_lap_ms": null,
          "position": 13,
          "year": 2014,
          "source_name": "Q3_BRUT_ALL_WITH_ID"
        },
        {
          "race_id": 900,
          "driver_id": 854,
          "team": "mclaren mercedes",
          "best_lap_time_raw": null,
          "best_lap_ms": null,
          "position": 9,
          "year": 2014,
          "source_name": "Q3_BRUT_ALL_WITH_ID"
        }
      ]
    },
    {
      "code": "GRILLE",
      "name": "Grille",
      "nb_rows": 22,
      "best_pos": 1,
      "best_ms": null,
      "rows": [
        {
          "race_id": 900,
          "driver_id": 764,
          "team": null,
          "best_lap_time_raw": null,
          "best_lap_ms": null,
          "position": 6,
          "year": null,
          "source_name": null
        },
        {
          "race_id": 900,
          "driver_id": 767,
          "team": null,
          "best_lap_time_raw": null,
          "best_lap_ms": null,
          "position": 9,
          "year": null,
          "source_name": null
        },
        {
          "race_id": 900,
          "driver_id": 771,
          "team": null,
          "best_lap_time_raw": null,
          "best_lap_ms": null,
          "position": 5,
          "year": null,
          "source_name": null
        },
        {
          "race_id": 900,
          "driver_id": 774,
          "team": null,
          "best_lap_time_raw": null,
          "best_lap_ms": null,
          "position": 7,
          "year": null,
          "source_name": null
        },
        {
          "race_id": 900,
          "driver_id": 805,
          "team": null,
          "best_lap_time_raw": null,
          "best_lap_ms": null,
          "position": 1,
          "year": null,
          "source_name": null
        },
        {
          "race_id": 900,
          "driver_id": 809,
          "team": null,
          "best_lap_time_raw": null,
          "best_lap_ms": null,
          "position": 2,
          "year": null,
          "source_name": null
        },
        {
          "race_id": 900,
          "driver_id": 812,
          "team": null,
          "best_lap_time_raw": null,
          "best_lap_ms": null,
          "position": 22,
          "year": null,
          "source_name": null
        },
        {
          "race_id": 900,
          "driver_id": 813,
          "team": null,
          "best_lap_time_raw": null,
          "best_lap_ms": null,
          "position": 10,
          "year": null,
          "source_name": null
        },
        {
          "race_id": 900,
          "driver_id": 819,
          "team": null,
          "best_lap_time_raw": null,
          "best_lap_ms": null,
          "position": 16,
          "year": null,
          "source_name": null
        },
        {
          "race_id": 900,
          "driver_id": 820,
          "team": null,
          "best_lap_time_raw": null,
          "best_lap_ms": null,
          "position": 18,
          "year": null,
          "source_name": null
        },
        {
          "race_id": 900,
          "driver_id": 824,
          "team": null,
          "best_lap_time_raw": null,
          "best_lap_ms": null,
          "position": 11,
          "year": null,
          "source_name": null
        },
        {
          "race_id": 900,
          "driver_id": 830,
          "team": null,
          "best_lap_time_raw": null,
          "best_lap_ms": null,
          "position": 17,
          "year": null,
          "source_name": null
        },
        {
          "race_id": 900,
          "driver_id": 831,
          "team": null,
          "best_lap_time_raw": null,
          "best_lap_ms": null,
          "position": 4,
          "year": null,
          "source_name": null
        },
        {
          "race_id": 900,
          "driver_id": 833,
          "team": null,
          "best_lap_time_raw": null,
          "best_lap_ms": null,
          "position": 13,
          "year": null,
          "source_name": null
        },
        {
          "race_id": 900,
          "driver_id": 840,
          "team": null,
          "best_lap_time_raw": null,
          "best_lap_ms": null,
          "position": 14,
          "year": null,
          "source_name": null
        },
        {
          "race_id": 900,
          "driver_id": 841,
          "team": null,
          "best_lap_time_raw": null,
          "best_lap_ms": null,
          "position": 19,
          "year": null,
          "source_name": null
        },
        {
          "race_id": 900,
          "driver_id": 842,
          "team": null,
          "best_lap_time_raw": null,
          "best_lap_ms": null,
          "position": 3,
          "year": null,
          "source_name": null
        },
        {
          "race_id": 900,
          "driver_id": 844,
          "team": null,
          "best_lap_time_raw": null,
          "best_lap_ms": null,
          "position": 21,
          "year": null,
          "source_name": null
        },
        {
          "race_id": 900,
          "driver_id": 845,
          "team": null,
          "best_lap_time_raw": null,
          "best_lap_ms": null,
          "position": 15,
          "year": null,
          "source_name": null
        },
        {
          "race_id": 900,
          "driver_id": 848,
          "team": null,
          "best_lap_time_raw": null,
          "best_lap_ms": null,
          "position": 20,
          "year": null,
          "source_name": null
        },
        {
          "race_id": 900,
          "driver_id": 852,
          "team": null,
          "best_lap_time_raw": null,
          "best_lap_ms": null,
          "position": 12,
          "year": null,
          "source_name": null
        },
        {
          "race_id": 900,
          "driver_id": 854,
          "team": null,
          "best_lap_time_raw": null,
          "best_lap_ms": null,
          "position": 8,
          "year": null,
          "source_name": null
        }
      ]
    },
    {
      "code": "MT",
      "name": "MT",
      "nb_rows": 22,
      "best_pos": 1,
      "best_ms": 97020,
      "rows": [
        {
          "race_id": 900,
          "driver_id": 755,
          "team": "mclaren mercedes",
          "best_lap_time_raw": "01:39.565",
          "best_lap_ms": 99565,
          "position": 10,
          "year": 2014,
          "source_name": "MT_BRUT_ALL",
          "lap_release": 37
        },
        {
          "race_id": 900,
          "driver_id": 758,
          "team": "ferrari",
          "best_lap_time_raw": "01:39.732",
          "best_lap_ms": 99732,
          "position": 12,
          "year": 2014,
          "source_name": "MT_BRUT_ALL",
          "lap_release": 53
        },
        {
          "race_id": 900,
          "driver_id": 762,
          "team": "ferrari",
          "best_lap_time_raw": "01:39.438",
          "best_lap_ms": 99438,
          "position": 8,
          "year": 2014,
          "source_name": "MT_BRUT_ALL",
          "lap_release": 35
        },
        {
          "race_id": 900,
          "driver_id": 765,
          "team": "williams mercedes",
          "best_lap_time_raw": "01:39.272",
          "best_lap_ms": 99272,
          "position": 5,
          "year": 2014,
          "source_name": "MT_BRUT_ALL",
          "lap_release": 40
        },
        {
          "race_id": 900,
          "driver_id": 796,
          "team": "mercedes",
          "best_lap_time_raw": "01:37.020",
          "best_lap_ms": 97020,
          "position": 1,
          "year": 2014,
          "source_name": "MT_BRUT_ALL",
          "lap_release": 49
        },
        {
          "race_id": 900,
          "driver_id": 800,
          "team": "mercedes",
          "best_lap_time_raw": "01:37.108",
          "best_lap_ms": 97108,
          "position": 2,
          "year": 2014,
          "source_name": "MT_BRUT_ALL",
          "lap_release": 49
        },
        {
          "race_id": 900,
          "driver_id": 803,
          "team": "sauber ferrari",
          "best_lap_time_raw": "01:41.791",
          "best_lap_ms": 101791,
          "position": 20,
          "year": 2014,
          "source_name": "MT_BRUT_ALL",
          "lap_release": 9
        },
        {
          "race_id": 900,
          "driver_id": 804,
          "team": "red bull racing renault",
          "best_lap_time_raw": "01:39.312",
          "best_lap_ms": 99312,
          "position": 6,
          "year": 2014,
          "source_name": "MT_BRUT_ALL",
          "lap_release": 18
        },
        {
          "race_id": 900,
          "driver_id": 810,
          "team": "lotus renault",
          "best_lap_time_raw": "01:39.443",
          "best_lap_ms": 99443,
          "position": 9,
          "year": 2014,
          "source_name": "MT_BRUT_ALL",
          "lap_release": 39
        },
        {
          "race_id": 900,
          "driver_id": 811,
          "team": "caterham renault",
          "best_lap_time_raw": "01:41.246",
          "best_lap_ms": 101246,
          "position": 18,
          "year": 2014,
          "source_name": "MT_BRUT_ALL",
          "lap_release": 17
        },
        {
          "race_id": 900,
          "driver_id": 815,
          "team": "force india mercedes",
          "best_lap_time_raw": "01:38.785",
          "best_lap_ms": 98785,
          "position": 3,
          "year": 2014,
          "source_name": "MT_BRUT_ALL",
          "lap_release": 37
        },
        {
          "race_id": 900,
          "driver_id": 821,
          "team": "lotus renault",
          "best_lap_time_raw": "01:39.666",
          "best_lap_ms": 99666,
          "position": 11,
          "year": 2014,
          "source_name": "MT_BRUT_ALL",
          "lap_release": 52
        },
        {
          "race_id": 900,
          "driver_id": 822,
          "team": "force india mercedes",
          "best_lap_time_raw": "01:39.320",
          "best_lap_ms": 99320,
          "position": 7,
          "year": 2014,
          "source_name": "MT_BRUT_ALL",
          "lap_release": 36
        },
        {
          "race_id": 900,
          "driver_id": 824,
          "team": "red bull racing renault",
          "best_lap_time_raw": "01:39.269",
          "best_lap_ms": 99269,
          "position": 4,
          "year": 2014,
          "source_name": "MT_BRUT_ALL",
          "lap_release": 38
        },
        {
          "race_id": 900,
          "driver_id": 831,
          "team": "str renault",
          "best_lap_time_raw": "01:41.650",
          "best_lap_ms": 101650,
          "position": 19,
          "year": 2014,
          "source_name": "MT_BRUT_ALL",
          "lap_release": 16
        },
        {
          "race_id": 900,
          "driver_id": 832,
          "team": "marussia ferrari",
          "best_lap_time_raw": "01:42.175",
          "best_lap_ms": 102175,
          "position": 22,
          "year": 2014,
          "source_name": "MT_BRUT_ALL",
          "lap_release": 44
        },
        {
          "race_id": 900,
          "driver_id": 833,
          "team": "williams mercedes",
          "best_lap_time_raw": "01:39.762",
          "best_lap_ms": 99762,
          "position": 13,
          "year": 2014,
          "source_name": "MT_BRUT_ALL",
          "lap_release": 50
        },
        {
          "race_id": 900,
          "driver_id": 835,
          "team": "marussia ferrari",
          "best_lap_time_raw": "01:41.825",
          "best_lap_ms": 101825,
          "position": 21,
          "year": 2014,
          "source_name": "MT_BRUT_ALL",
          "lap_release": 48
        },
        {
          "race_id": 900,
          "driver_id": 836,
          "team": "sauber ferrari",
          "best_lap_time_raw": "01:40.698",
          "best_lap_ms": 100698,
          "position": 16,
          "year": 2014,
          "source_name": "MT_BRUT_ALL",
          "lap_release": 32
        },
        {
          "race_id": 900,
          "driver_id": 839,
          "team": "caterham renault",
          "best_lap_time_raw": "01:41.134",
          "best_lap_ms": 101134,
          "position": 17,
          "year": 2014,
          "source_name": "MT_BRUT_ALL",
          "lap_release": 28
        },
        {
          "race_id": 900,
          "driver_id": 843,
          "team": "str renault",
          "best_lap_time_raw": "01:40.160",
          "best_lap_ms": 100160,
          "position": 15,
          "year": 2014,
          "source_name": "MT_BRUT_ALL",
          "lap_release": 12
        },
        {
          "race_id": 900,
          "driver_id": 845,
          "team": "mclaren mercedes",
          "best_lap_time_raw": "01:40.108",
          "best_lap_ms": 100108,
          "position": 14,
          "year": 2014,
          "source_name": "MT_BRUT_ALL",
          "lap_release": 40
        }
      ]
    },
    {
      "code": "COURSE",
      "name": "Course",
      "nb_rows": 22,
      "best_pos": 1,
      "best_ms": null,
      "rows": [
        {
          "race_id": 900,
          "driver_id": 764,
          "position": 17,
          "num_car": "22.0",
          "teams_name": "McLaren",
          "motor_name": "Mercedes",
          "laps_completed": 55,
          "delta": "Embrayage",
          "penalites": null,
          "rank_affichage": "17",
          "ab": "Mecanique",
          "source_file": null
        },
        {
          "race_id": 900,
          "driver_id": 767,
          "position": 9,
          "num_car": "14.0",
          "teams_name": "Ferrari",
          "motor_name": "Ferrari",
          "laps_completed": 57,
          "delta": "1h 40m 15.338s ( +32",
          "penalites": null,
          "rank_affichage": "9",
          "ab": null,
          "source_file": null
        },
        {
          "race_id": 900,
          "driver_id": 771,
          "position": 10,
          "num_car": "7.0",
          "teams_name": "Ferrari",
          "motor_name": "Ferrari",
          "laps_completed": 57,
          "delta": "1h 40m 16.205s ( +33",
          "penalites": null,
          "rank_affichage": "10",
          "ab": null,
          "source_file": null
        },
        {
          "race_id": 900,
          "driver_id": 774,
          "position": 7,
          "num_car": "19.0",
          "teams_name": "Williams",
          "motor_name": "Mercedes",
          "laps_completed": 57,
          "delta": "1h 40m 14.008s ( +31",
          "penalites": null,
          "rank_affichage": "7",
          "ab": null,
          "source_file": null
        },
        {
          "race_id": 900,
          "driver_id": 805,
          "position": 2,
          "num_car": "6.0",
          "teams_name": "Mercedes",
          "motor_name": "Mercedes",
          "laps_completed": 57,
          "delta": "1h 39m 43.828s ( +01",
          "penalites": null,
          "rank_affichage": "2",
          "ab": null,
          "source_file": null
        },
        {
          "race_id": 900,
          "driver_id": 809,
          "position": 1,
          "num_car": "44.0",
          "teams_name": "Mercedes",
          "motor_name": "Mercedes",
          "laps_completed": 57,
          "delta": "1h 39m 42.743s ( 185",
          "penalites": null,
          "rank_affichage": "1",
          "ab": null,
          "source_file": null
        },
        {
          "race_id": 900,
          "driver_id": 812,
          "position": 0,
          "num_car": "99.0",
          "teams_name": "Sauber",
          "motor_name": "Ferrari",
          "laps_completed": 17,
          "delta": "Accrochage",
          "penalites": null,
          "rank_affichage": "22",
          "ab": "Pilote",
          "source_file": null
        },
        {
          "race_id": 900,
          "driver_id": 813,
          "position": 6,
          "num_car": "1.0",
          "teams_name": "Red Bull",
          "motor_name": "Renault",
          "laps_completed": 57,
          "delta": "1h 40m 12.622s ( +29",
          "penalites": null,
          "rank_affichage": "6",
          "ab": null,
          "source_file": null
        },
        {
          "race_id": 900,
          "driver_id": 819,
          "position": 12,
          "num_car": "8.0",
          "teams_name": "Lotus",
          "motor_name": "Renault",
          "laps_completed": 57,
          "delta": "1h 40m 25.886s ( +43",
          "penalites": null,
          "rank_affichage": "12",
          "ab": null,
          "source_file": null
        },
        {
          "race_id": 900,
          "driver_id": 820,
          "position": 15,
          "num_car": "10.0",
          "teams_name": "Caterham",
          "motor_name": "Renault",
          "laps_completed": 57,
          "delta": "1h 41m 10.643s ( +1m",
          "penalites": null,
          "rank_affichage": "15",
          "ab": null,
          "source_file": null
        },
        {
          "race_id": 900,
          "driver_id": 824,
          "position": 5,
          "num_car": "27.0",
          "teams_name": "Force India",
          "motor_name": "Mercedes",
          "laps_completed": 57,
          "delta": "1h 40m 11.397s ( +28",
          "penalites": null,
          "rank_affichage": "5",
          "ab": null,
          "source_file": null
        },
        {
          "race_id": 900,
          "driver_id": 830,
          "position": 14,
          "num_car": "13.0",
          "teams_name": "Lotus",
          "motor_name": "Renault",
          "laps_completed": 57,
          "delta": "1h 40m 45.546s ( +1m",
          "penalites": null,
          "rank_affichage": "14",
          "ab": null,
          "source_file": null
        },
        {
          "race_id": 900,
          "driver_id": 831,
          "position": 3,
          "num_car": "11.0",
          "teams_name": "Force India",
          "motor_name": "Mercedes",
          "laps_completed": 57,
          "delta": "1h 40m 06.810s ( +24",
          "penalites": null,
          "rank_affichage": "3",
          "ab": null,
          "source_file": null
        },
        {
          "race_id": 900,
          "driver_id": 833,
          "position": 4,
          "num_car": "3.0",
          "teams_name": "Red Bull",
          "motor_name": "Renault",
          "laps_completed": 57,
          "delta": "1h 40m 07.232s ( +24",
          "penalites": null,
          "rank_affichage": "4",
          "ab": null,
          "source_file": null
        },
        {
          "race_id": 900,
          "driver_id": 840,
          "position": 0,
          "num_car": "25.0",
          "teams_name": "Toro Rosso",
          "motor_name": "Renault",
          "laps_completed": 18,
          "delta": "Accrochage",
          "penalites": null,
          "rank_affichage": "21",
          "ab": "Pilote",
          "source_file": null
        },
        {
          "race_id": 900,
          "driver_id": 841,
          "position": 16,
          "num_car": "17.0",
          "teams_name": "Marussia",
          "motor_name": "Ferrari",
          "laps_completed": 56,
          "delta": null,
          "penalites": null,
          "rank_affichage": "16",
          "ab": null,
          "source_file": null
        },
        {
          "race_id": 900,
          "driver_id": 842,
          "position": 8,
          "num_car": "77.0",
          "teams_name": "Williams",
          "motor_name": "Mercedes",
          "laps_completed": 57,
          "delta": "1h 40m 14.619s ( +31",
          "penalites": null,
          "rank_affichage": "8",
          "ab": null,
          "source_file": null
        },
        {
          "race_id": 900,
          "driver_id": 844,
          "position": 13,
          "num_car": "4.0",
          "teams_name": "Marussia",
          "motor_name": "Ferrari",
          "laps_completed": 57,
          "delta": "1h 40m 42.652s ( +59",
          "penalites": null,
          "rank_affichage": "13",
          "ab": null,
          "source_file": null
        },
        {
          "race_id": 900,
          "driver_id": 845,
          "position": 0,
          "num_car": "21.0",
          "teams_name": "Sauber",
          "motor_name": "Ferrari",
          "laps_completed": 39,
          "delta": "Accrochage",
          "penalites": null,
          "rank_affichage": "19",
          "ab": "Pilote",
          "source_file": null
        },
        {
          "race_id": 900,
          "driver_id": 848,
          "position": 0,
          "num_car": "9.0",
          "teams_name": "Caterham",
          "motor_name": "Renault",
          "laps_completed": 33,
          "delta": "Fuite d'huile",
          "penalites": null,
          "rank_affichage": "20",
          "ab": "Mecanique",
          "source_file": null
        },
        {
          "race_id": 900,
          "driver_id": 852,
          "position": 11,
          "num_car": "26.0",
          "teams_name": "Toro Rosso",
          "motor_name": "Renault",
          "laps_completed": 57,
          "delta": "1h 40m 24.085s ( +41",
          "penalites": null,
          "rank_affichage": "11",
          "ab": null,
          "source_file": null
        },
        {
          "race_id": 900,
          "driver_id": 854,
          "position": 0,
          "num_car": "20.0",
          "teams_name": "McLaren",
          "motor_name": "Mercedes",
          "laps_completed": 40,
          "delta": "Embrayage",
          "penalites": null,
          "rank_affichage": "18",
          "ab": "Mecanique",
          "source_file": null
        }
      ]
    }
  ]
}